<?xml version="1.0"?>
<?mso-application progid="Excel.Sheet"?>
<Workbook xmlns="urn:schemas-microsoft-com:office:spreadsheet"
 xmlns:o="urn:schemas-microsoft-com:office:office"
 xmlns:x="urn:schemas-microsoft-com:office:excel"
 xmlns:ss="urn:schemas-microsoft-com:office:spreadsheet"
 xmlns:html="http://www.w3.org/TR/REC-html40">
 <Styles>
  <Style ss:ID="Default" ss:Name="Normal">
   <Alignment ss:Vertical="Bottom"/>
   <Borders/>
   <Font ss:FontName="Aptos Narrow" x:Family="Swiss" ss:Size="11"
    ss:Color="#000000"/>
   <Interior/>
   <NumberFormat/>
   <Protection/>
  </Style>
  <Style ss:ID="s18" ss:Name="Hyperlink">
   <Font ss:FontName="Aptos Narrow" x:Family="Swiss" ss:Size="11"
    ss:Color="#467886" ss:Underline="Single"/>
  </Style>
  <Style ss:ID="s20">
   <Font ss:FontName="Aptos Narrow" x:Family="Swiss" ss:Size="11"
    ss:Color="#000000" ss:Bold="1"/>
  </Style>
  <Style ss:ID="s32">
   <Alignment ss:Horizontal="Left" ss:Vertical="Bottom"/>
   <Font ss:FontName="Aptos Narrow" x:Family="Swiss" ss:Size="16"
    ss:Color="#000000" ss:Bold="1"/>
  </Style>
  <Style ss:ID="s33">
   <Font ss:FontName="Aptos Narrow" x:Family="Swiss" ss:Size="11"
    ss:Color="#000000" ss:Italic="1"/>
  </Style>
  <Style ss:ID="s34">
   <Font ss:FontName="Aptos Narrow" x:Family="Swiss" ss:Size="11"
    ss:Color="#000000"/>
  </Style>
  <Style ss:ID="s35">
   <Borders>
    <Border ss:Position="Bottom" ss:LineStyle="Continuous" ss:Weight="1"
     ss:Color="#747474"/>
   </Borders>
   <Font ss:FontName="Aptos Narrow" x:Family="Swiss" ss:Size="14"
    ss:Color="#000000" ss:Bold="1" ss:Italic="1"/>
  </Style>
  <Style ss:ID="s36">
   <Font ss:FontName="Aptos Narrow" x:Family="Swiss" ss:Size="11"
    ss:Color="#808080"/>
  </Style>
 </Styles>
 <Names>
  <NamedRange ss:Name="_AtRisk_SimSetting_AutomaticallyGenerateReports"
   ss:RefersTo="=FALSE" ss:Hidden="1"/>
  <NamedRange ss:Name="_AtRisk_SimSetting_AutomaticResultsDisplayMode"
   ss:RefersTo="=0" ss:Hidden="1"/>
  <NamedRange ss:Name="_AtRisk_SimSetting_ConvergenceConfidenceLevel"
   ss:RefersTo="=0.95" ss:Hidden="1"/>
  <NamedRange ss:Name="_AtRisk_SimSetting_ConvergencePercentileToTest"
   ss:RefersTo="=0.9" ss:Hidden="1"/>
  <NamedRange ss:Name="_AtRisk_SimSetting_ConvergencePerformMeanTest"
   ss:RefersTo="=TRUE" ss:Hidden="1"/>
  <NamedRange ss:Name="_AtRisk_SimSetting_ConvergencePerformPercentileTest"
   ss:RefersTo="=FALSE" ss:Hidden="1"/>
  <NamedRange ss:Name="_AtRisk_SimSetting_ConvergencePerformStdDeviationTest"
   ss:RefersTo="=FALSE" ss:Hidden="1"/>
  <NamedRange ss:Name="_AtRisk_SimSetting_ConvergenceTestAllOutputs"
   ss:RefersTo="=TRUE" ss:Hidden="1"/>
  <NamedRange ss:Name="_AtRisk_SimSetting_ConvergenceTestingPeriod"
   ss:RefersTo="=100" ss:Hidden="1"/>
  <NamedRange ss:Name="_AtRisk_SimSetting_ConvergenceTolerance" ss:RefersTo="=0.03"
   ss:Hidden="1"/>
  <NamedRange ss:Name="_AtRisk_SimSetting_LiveUpdate" ss:RefersTo="=TRUE"
   ss:Hidden="1"/>
  <NamedRange ss:Name="_AtRisk_SimSetting_LiveUpdatePeriod" ss:RefersTo="=-1"
   ss:Hidden="1"/>
  <NamedRange ss:Name="_AtRisk_SimSetting_RandomNumberGenerator" ss:RefersTo="=0"
   ss:Hidden="1"/>
  <NamedRange ss:Name="_AtRisk_SimSetting_ReportsList" ss:RefersTo="=0"
   ss:Hidden="1"/>
  <NamedRange ss:Name="_AtRisk_SimSetting_SimNameCount" ss:RefersTo="=0"
   ss:Hidden="1"/>
  <NamedRange ss:Name="_AtRisk_SimSetting_StdRecalcBehavior" ss:RefersTo="=0"
   ss:Hidden="1"/>
  <NamedRange ss:Name="_AtRisk_SimSetting_StdRecalcWithoutRiskStatic"
   ss:RefersTo="=0" ss:Hidden="1"/>
  <NamedRange ss:Name="_AtRisk_SimSetting_StdRecalcWithoutRiskStaticPercentile"
   ss:RefersTo="=0.5" ss:Hidden="1"/>
  <NamedRange ss:Name="_xlpm.\\CommandName" ss:RefersTo="=#NAME?" ss:Hidden="1"/>
  <NamedRange ss:Name="_xlpm.\\Description" ss:RefersTo="=#NAME?" ss:Hidden="1"/>
  <NamedRange ss:Name="_xlpm.\\LambdaName" ss:RefersTo="=#NAME?" ss:Hidden="1"/>
  <NamedRange ss:Name="_xlpm.c" ss:RefersTo="=#NAME?" ss:Hidden="1"/>
  <NamedRange ss:Name="_xlpm.dates" ss:RefersTo="=#NAME?" ss:Hidden="1"/>
  <NamedRange ss:Name="_xlpm.f" ss:RefersTo="=#NAME?" ss:Hidden="1"/>
  <NamedRange ss:Name="_xlpm.number" ss:RefersTo="=#NAME?" ss:Hidden="1"/>
  <NamedRange ss:Name="_xlpm.r" ss:RefersTo="=#NAME?" ss:Hidden="1"/>
  <NamedRange ss:Name="_xlpm.Reference" ss:RefersTo="=#NAME?" ss:Hidden="1"/>
  <NamedRange ss:Name="_xlpm.s" ss:RefersTo="=#NAME?" ss:Hidden="1"/>
  <NamedRange ss:Name="_xlpm.x" ss:RefersTo="=#NAME?" ss:Hidden="1"/>
  <NamedRange ss:Name="IQ_FWD_CY" ss:RefersTo="=10001" ss:Hidden="1"/>
  <NamedRange ss:Name="IQ_FWD_CY1" ss:RefersTo="=10002" ss:Hidden="1"/>
  <NamedRange ss:Name="IQ_FWD_CY2" ss:RefersTo="=10003" ss:Hidden="1"/>
  <NamedRange ss:Name="IQ_FWD_FY" ss:RefersTo="=1001" ss:Hidden="1"/>
  <NamedRange ss:Name="IQ_FWD_FY1" ss:RefersTo="=1002" ss:Hidden="1"/>
  <NamedRange ss:Name="IQ_FWD_FY2" ss:RefersTo="=1003" ss:Hidden="1"/>
  <NamedRange ss:Name="IQ_FWD_Q" ss:RefersTo="=501" ss:Hidden="1"/>
  <NamedRange ss:Name="IQ_FWD_Q1" ss:RefersTo="=502" ss:Hidden="1"/>
  <NamedRange ss:Name="IQ_FWD_Q2" ss:RefersTo="=503" ss:Hidden="1"/>
  <NamedRange ss:Name="IQ_LATESTK" ss:RefersTo="=1000" ss:Hidden="1"/>
  <NamedRange ss:Name="IQ_LATESTQ" ss:RefersTo="=500" ss:Hidden="1"/>
  <NamedRange ss:Name="IQ_LTMMONTH" ss:RefersTo="=120000" ss:Hidden="1"/>
  <NamedRange ss:Name="IQ_TODAY" ss:RefersTo="=0" ss:Hidden="1"/>
  <NamedRange ss:Name="IQ_YTDMONTH" ss:RefersTo="=130000" ss:Hidden="1"/>
  <NamedRange ss:Name="OrdinalSuffix"
   ss:RefersTo="=LAMBDA(number, LET(&#10;   \\LambdaName, &quot;OrdinalSuffix&quot;,&#10;   IF(&#10;      (MOD(number, 100) &gt; 10) * (MOD(number, 100) &lt; 14),&#10;      &quot;th&quot;,&#10;      SWITCH(MOD(number, 10), 1, &quot;st&quot;, 2, &quot;nd&quot;, 3, &quot;rd&quot;, &quot;th&quot;)&#10;   )&#10;))"/>
  <NamedRange ss:Name="RiskAfterRecalcMacro" ss:RefersTo="=&quot;&quot;"
   ss:Hidden="1"/>
  <NamedRange ss:Name="RiskAfterSimMacro" ss:RefersTo="=&quot;&quot;" ss:Hidden="1"/>
  <NamedRange ss:Name="RiskBeforeRecalcMacro" ss:RefersTo="=&quot;&quot;"
   ss:Hidden="1"/>
  <NamedRange ss:Name="RiskBeforeSimMacro" ss:RefersTo="=&quot;&quot;"
   ss:Hidden="1"/>
  <NamedRange ss:Name="RiskCollectDistributionSamples" ss:RefersTo="=2"
   ss:Hidden="1"/>
  <NamedRange ss:Name="RiskFixedSeed" ss:RefersTo="=1" ss:Hidden="1"/>
  <NamedRange ss:Name="RiskHasSettings" ss:RefersTo="=5" ss:Hidden="1"/>
  <NamedRange ss:Name="RiskMinimizeOnStart" ss:RefersTo="=FALSE" ss:Hidden="1"/>
  <NamedRange ss:Name="RiskMonitorConvergence" ss:RefersTo="=FALSE" ss:Hidden="1"/>
  <NamedRange ss:Name="RiskNumIterations" ss:RefersTo="=5000" ss:Hidden="1"/>
  <NamedRange ss:Name="RiskNumSimulations" ss:RefersTo="=1" ss:Hidden="1"/>
  <NamedRange ss:Name="RiskPauseOnError" ss:RefersTo="=FALSE" ss:Hidden="1"/>
  <NamedRange ss:Name="RiskRunAfterRecalcMacro" ss:RefersTo="=FALSE" ss:Hidden="1"/>
  <NamedRange ss:Name="RiskRunAfterSimMacro" ss:RefersTo="=FALSE" ss:Hidden="1"/>
  <NamedRange ss:Name="RiskRunBeforeRecalcMacro" ss:RefersTo="=FALSE" ss:Hidden="1"/>
  <NamedRange ss:Name="RiskRunBeforeSimMacro" ss:RefersTo="=FALSE" ss:Hidden="1"/>
  <NamedRange ss:Name="RiskSamplingType" ss:RefersTo="=3" ss:Hidden="1"/>
  <NamedRange ss:Name="RiskStandardRecalc" ss:RefersTo="=1" ss:Hidden="1"/>
  <NamedRange ss:Name="RiskUpdateDisplay" ss:RefersTo="=TRUE" ss:Hidden="1"/>
  <NamedRange ss:Name="RiskUseDifferentSeedForEachSim" ss:RefersTo="=FALSE"
   ss:Hidden="1"/>
  <NamedRange ss:Name="RiskUseFixedSeed" ss:RefersTo="=FALSE" ss:Hidden="1"/>
  <NamedRange ss:Name="RiskUseMultipleCPUs" ss:RefersTo="=FALSE" ss:Hidden="1"/>
  <NamedRange ss:Name="ShowFormulas"
   ss:RefersTo="=LAMBDA(Reference, LET(&#10;   \\LambdaName, &quot;ShowFormulas&quot;,&#10;   \\CommandName, &quot;Show Formulas&quot;,&#10;   c, Reference,&#10;   f, TOCOL(ADDRESS(ROW(c), COLUMN(c), 4) &amp; &quot;: &quot; &amp; FORMULATEXT(c), 3),&#10;   r, DROP(REDUCE({&quot;&quot;}, f, LAMBDA(s,x, VSTACK(s, TEXTSPLIT(x, , &quot;&#10;&quot;)))), 1),&#10;   r&#10;))"/>
 </Names>
 <Worksheet ss:Name="Commands">
  <Table ss:ExpandedColumnCount="5" ss:ExpandedRowCount="26"
   ss:DefaultRowHeight="15">
   <Column ss:AutoFitWidth="0" ss:Width="14.25"/>
   <Column ss:AutoFitWidth="0" ss:Width="145.5"/>
   <Column ss:AutoFitWidth="0" ss:Width="89.25"/>
   <Column ss:AutoFitWidth="0" ss:Width="633.75"/>
   <Row ss:Height="21">
    <Cell ss:StyleID="s32"><Data ss:Type="String">Denis Robot</Data></Cell>
    <Cell ss:StyleID="s20"/>
    <Cell ss:StyleID="s20"/>
    <Cell ss:StyleID="s33"/>
   </Row>
   <Row>
    <Cell ss:StyleID="s34"/>
    <Cell ss:StyleID="s20"/>
    <Cell ss:StyleID="s20"/>
    <Cell ss:StyleID="s33"/>
   </Row>
   <Row ss:Height="18.75">
    <Cell ss:StyleID="s35"/>
    <Cell ss:StyleID="s35"><Data ss:Type="String">Ordinal Suffixes in English</Data></Cell>
    <Cell ss:StyleID="s35"/>
    <Cell ss:StyleID="s35"/>
   </Row>
   <Row>
    <Cell ss:StyleID="s34"/>
    <Cell ss:StyleID="s20"/>
    <Cell ss:StyleID="s20"/>
    <Cell ss:StyleID="s33"/>
   </Row>
   <Row>
    <Cell ss:StyleID="s34"/>
    <Cell ss:StyleID="s20"><Data ss:Type="String">Ordinal Suffix</Data></Cell>
    <Cell ss:StyleID="s36"><Data ss:Type="String">Lambda Formula</Data></Cell>
    <Cell ss:StyleID="s33"/>
    <Cell><Data ss:Type="String">Requires selected cells to contain numbers</Data></Cell>
   </Row>
   <Row>
    <Cell ss:Index="2" ss:StyleID="s20"><Data ss:Type="String">Ordinal Number</Data></Cell>
    <Cell ss:StyleID="s36"><Data ss:Type="String">Lambda Formula</Data></Cell>
    <Cell ss:StyleID="s33"><Data ss:Type="String">Convert numbers to text including the ordinal suffixes &quot;th&quot;, &quot;st&quot;, &quot;nd&quot; and &quot;rd&quot;</Data></Cell>
    <Cell><Data ss:Type="String">Requires selected cells to contain numbers</Data></Cell>
   </Row>
   <Row>
    <Cell ss:Index="2" ss:StyleID="s20"><Data ss:Type="String">Ordinal Date</Data></Cell>
    <Cell ss:StyleID="s36"><Data ss:Type="String">Lambda Formula</Data></Cell>
    <Cell ss:StyleID="s33"><Data ss:Type="String">Convert dates into long format text including the ordinal suffixes &quot;th&quot;, &quot;st&quot;, &quot;nd&quot; and &quot;rd&quot;</Data></Cell>
    <Cell><Data ss:Type="String">Requires selected cells to contain dates</Data></Cell>
   </Row>
   <Row ss:Index="15" ss:Height="18.75">
    <Cell ss:Index="2" ss:StyleID="s35"><Data ss:Type="String">Utilities</Data></Cell>
    <Cell ss:StyleID="s35"/>
    <Cell ss:StyleID="s35"/>
   </Row>
   <Row ss:Index="17">
    <Cell ss:Index="2" ss:StyleID="s20"><Data ss:Type="String">Show Formulas</Data></Cell>
    <Cell ss:StyleID="s36"><Data ss:Type="String">Lambda Formula</Data></Cell>
    <Cell><Data ss:Type="String">Display the text of all formulas found in a selected range of cells</Data></Cell>
   </Row>
   <Row ss:Index="22" ss:Height="18.75">
    <Cell ss:Index="2" ss:StyleID="s35"><Data ss:Type="String">To Do</Data></Cell>
    <Cell ss:StyleID="s35"/>
    <Cell ss:StyleID="s35"/>
   </Row>
   <Row ss:Index="24">
    <Cell ss:Index="2"><Data ss:Type="String">improve show formulas</Data></Cell>
   </Row>
   <Row>
    <Cell ss:Index="2"><Data ss:Type="String">other countries ordinals</Data></Cell>
    <Cell ss:StyleID="s18" ss:HRef="https://en.wikipedia.org/wiki/Ordinal_indicator"><Data
      ss:Type="String">Ordinal indicator - Wikipedia</Data></Cell>
   </Row>
   <Row>
    <Cell ss:Index="2"><Data ss:Type="String">ordinals with superscript (VBA)</Data></Cell>
    <Cell ss:StyleID="s18" ss:HRef="https://answers.microsoft.com/en-us/msoffice/forum/all/how-to-write-a-macro-to-modify-and-superscript/4e314ec8-9cbd-41b3-a24f-45bfb3919d3b"><Data
      ss:Type="String">How to write a Macro to modify and superscript numbers - Microsoft Community</Data></Cell>
   </Row>
  </Table>
 </Worksheet>
</Workbook>
